acemcp/__init__.py
acemcp/config.py
acemcp/index/__init__.py
acemcp/index/manager.py
acemcp/logging_config.py
acemcp/py.typed
acemcp/server.py
acemcp/tools/__init__.py
acemcp/tools/search_context.py
acemcp/web/__init__.py
acemcp/web/app.py
acemcp/web/log_handler.py
acemcp/web/templates/index.html
acemcp-0.2.2.dist-info/WHEEL
acemcp-0.2.2.dist-info/entry_points.txt
acemcp-0.2.2.dist-info/METADATA
acemcp-0.2.2.dist-info/RECORD
