Metadata-Version: 2.3
Name: acemcp
Version: 0.2.2
Summary: MCP server for codebase indexing and semantic search with multi-encoding support and .gitignore integration
Author: wmymz
Author-email: wmymz <wmymz@icloud.com>
Requires-Dist: dynaconf>=3.2.12
Requires-Dist: loguru>=0.7.3
Requires-Dist: mcp[cli]>=1.22.0
Requires-Dist: httpx[socks]>=0.28.1
Requires-Dist: fastapi>=0.123.3
Requires-Dist: uvicorn[standard]>=0.34.0
Requires-Dist: toml>=0.10.2
Requires-Dist: websockets>=14.1
Requires-Dist: pathspec>=0.12.1
Requires-Python: >=3.10
